[{"ticker":"DOGZ","table":"SEP","permaticker":120512,"name":"DOGNESS (INTERNATIONAL) CORP","exchange":"NASDAQ","isdelisted":false,"category":"ADR Common Stock","cusips":"G2788T103 G2788T111","siccode":3990.0,"sicsector":"Manufacturing","sicindustry":"Miscellaneous Manufacturing Industries","famasector":null,"famaindustry":null,"sector":"Consumer Cyclical","industry":"Leisure","scalemarketcap":"3 - Small","scalerevenue":"1 - Nano","relatedtickers":null,"currency":"USD","location":"China","lastupdated":"2026-01-07","firstadded":"2018-02-19","firstpricedate":"2017-12-20","lastpricedate":"2026-01-07","firstquarter":"2016-06-30","lastquarter":"2025-06-30","secfilings":"https:\/\/www.sec.gov\/cgi-bin\/browse-edgar?action=getcompany&CIK=0001707303","companysite":"http:\/\/www.dognesspet.com","open":10.94,"close":10.96,"high":11.177,"low":10.7,"volume":124123,"fxusd":1.0,"marketcap":139528012.0,"index":505998,"datekey":"2025-06-30","reportperiod":"2025-06-30T00:00:00.000","fiscalperiod":"2025-Q4","accoci":-9413583.0,"assets":116846586.0,"assetsavg":108023708.0,"assetsc":20471674.0,"assetsnc":96374912.0,"assetturnover":0.192,"bvps":7.29,"capex":877640.0,"cashneq":12831485.0,"cashnequsd":12831485.0,"cor":15682213.0,"consolinc":-5101237.0,"currentratio":3.353,"de":0.1556,"debt":15207828.0,"debtc":2219984.0,"debtnc":12987844.0,"debtusd":15207828.0,"deferredrev":0.0,"depamor":3440152.0,"deposits":187846.0,"divyield":0.0,"dps":0.0,"ebit":-6258826.0,"ebitda":-2818674.0,"ebitdamargin":-0.136,"ebitdausd":-2818674.0,"ebitusd":-6258826.0,"ebt":-6178323.0,"eps":-0.38,"epsdil":-0.38,"epsusd":-0.38,"equity":97752825.0,"equityavg":87081816.0,"equityusd":97752782.0,"ev":141904355.0,"evebit":-22.67,"evebitda":-50.34,"fcf":1444728.0,"fcfps":0.108,"gp":5025494.0,"grossmargin":0.243,"intangibles":1748755.0,"intexp":-80503.0,"invcap":111368257.0,"invcapavg":105778232.0,"inventory":2719790.0,"investments":20656752.0,"investmentsc":0.0,"investmentsnc":20656752.0,"liabilities":19093761.0,"liabilitiesc":6105917.0,"liabilitiesnc":12987844.0,"ncf":5875051.0,"ncfbus":0.0,"ncfcommon":5879390.0,"ncfdebt":-1476128.0,"ncfdiv":0.0,"ncff":4403262.0,"ncfi":877640.0,"ncfinv":0.0,"ncfo":567088.0,"ncfx":27061.0,"netinc":-5101237.0,"netinccmn":-5101237.0,"netinccmnusd":-5101237.0,"netincdis":0.0,"netincnci":0.0,"netmargin":-0.246,"opex":11820142.0,"opinc":-6794648.0,"payables":1648424.0,"payoutratio":0.0,"pb":1.43,"pe":-40.928,"pe1":-28.84,"ppnenet":71426583.0,"prefdivis":0.0,"price":16.4,"ps":10.082,"ps1":6.74,"receivables":1422711.0,"retearn":-10492946.0,"revenue":20707707.0,"revenueusd":20707707.0,"rnd":1115108.0,"roa":-0.047,"roe":-0.059,"roic":-0.059,"ros":-0.302,"sbcomp":466044.0,"sgna":10477711.0,"sharefactor":1.0,"sharesbas":12730658.0,"shareswa":13408261.0,"shareswadil":13408261.0,"sps":1.544,"tangibles":115097831.0,"taxassets":2542822.0,"taxexp":-1077086.0,"taxliabilities":566682.0,"tbvps":8.584,"workingcapital":14365757.0,"date":"2025-06-30T00:00:00.000","shares":12730658.0,"net_workingcapital":7172368.0,"discretionary_capex":11078564.0,"fcfadj":-10511476.0,"fcfpsadj":-0.83,"revenuepct":0.0222,"revenueyoy":0.1776,"roc_revenueyoy":2.6468,"revenuecagr":-0.0772,"netincadj":-5101237.0,"epsadj":-0.4,"epspct":0.0256,"epsyoy":0.4412,"epsyoy1":0.4935,"epsyoy_3q":0.3188,"epsyoy_3q1":0.0,"epscagr":0.0,"netinccagr":0.0,"ebitmargin":-0.3022,"ebitcagr":0.0,"ebitdacagr":0.0,"ebitdayoy":0.25,"peg":null,"dpscagr":0.0,"dpscagr5y":0.0,"dpscagr10y":0.0,"epsrank":80,"fcfpct":2.6119,"fcfyoy":1.11,"fcfcagr":0.4192,"fcfadjyoy":0.8699,"fcfadjcagr":0.0,"fcfusd":1444728.0,"avgroa":-0.0381,"avgroe":-0.0473,"avgroic":-0.0441,"roce":-0.0565,"avgroce":-0.0488,"fcfadjusd":-10511476.0,"cfc":-0.0835,"icr":-77.75,"netdebt":2376343.0,"dtfcf":1.6448,"dtebitda":-0.8431,"quickratio":5.7176,"reinvestrate":0.5524,"debtyield":0.0106,"bbyield":-0.0421,"shyield":-0.0421,"FS_ROA":0,"FCFTA":0.012364315,"FS_FCFTA":1,"ACCRUAL":-0.0530965192,"FS_ACCRUAL":1,"FS_\u0394LEVER":1,"FS_\u0394LIQUID":1,"FS_NEQISS":1,"FS_\u0394ROA":1,"FS_\u0394FCFTA":1,"FS_\u0394MARGIN":0,"FS_\u0394TURN":0,"fsscore":7,"smrrank":40,"evrevenue":6.85,"ipb":1.45,"fcfyield":0.0104,"returnytd":3.4,"volumeavg3m":231271,"beta1y":0.3,"volumeusd":1359040.0,"pct":-0.36,"close1":11.0,"volume1":2195000.0,"low1":10.5,"high1":11.51,"pct1":-3.42,"maxc20":11.39,"minc20":9.52,"max252":48.3,"min252":6.81,"maxc252":44.32,"minc252":7.55,"chg5":5.18,"chg10":8.51,"chg1m":-4.86,"chg1q":-18.63,"chg2q":16.22,"chg3q":-62.23,"chg1y":-70.05,"rs1y":-30.664,"adx":15.6296208935,"max_adx20":24.255290288,"roc20":-0.0403,"roc100":-0.2238,"roc200":-0.6757,"mom3":0.855233853,"mom6":1.2216330859,"mom12":0.3147540984,"sma5":10.95,"sma10":10.599,"sma20":10.469,"sma50":11.17912,"sma100":12.23291,"sma150":13.3766066667,"sma200":15.40818,"sma250":18.500624,"ema5":10.8995639614,"ema8":10.7754116509,"ema10":10.7228800793,"ema12":10.6934635785,"ema15":10.68184221,"ema20":10.716826538,"ema26":10.8044043341,"tenkan_sen":10.755,"kijun_sen":11.025,"senkou_span_a":12.21375,"senkou_span_b":13.095,"senkou_span_b1":13.095,"chikou_span":null,"avgvolume":193104.0,"avgvolumeusd":2125472.3199999998,"avgvolumeusd1m":3240929.5,"adr":0.5,"atr":0.5509111001,"std20":45.15,"std60":64.26,"std100":90.67,"std252":139.89,"rv3":70.85,"rv5":51.37,"rv20":45.36,"rv60":66.74,"rv100":99.61,"rv252":157.01,"ADline":384634.1554361301,"ADscore":86.2902191449,"ADrank":79,"rsrank":14,"rank_mom6":78,"rank_mom12":9,"rank_mom3":26,"rank_volume3m":42,"rank_volume1m":48,"close_date":"2026-01-07T00:00:00.000","comprating":56,"qualrank":5,"finalcomp":46}]