[{"ticker":"DTIL","table":"SEP","permaticker":111075,"name":"PRECISION BIOSCIENCES INC","exchange":"NASDAQ","isdelisted":false,"category":"Domestic Common Stock","cusips":"74019P108 74019P207","siccode":2836.0,"sicsector":"Manufacturing","sicindustry":"Biological Products (No Disgnostic Substances)","famasector":null,"famaindustry":"Pharmaceutical Products","sector":"Healthcare","industry":"Biotechnology","scalemarketcap":"3 - Small","scalerevenue":"2 - Micro","relatedtickers":null,"currency":"USD","location":"North Carolina; U.S.A","lastupdated":"2026-01-07","firstadded":"2019-03-28","firstpricedate":"2019-03-28","lastpricedate":"2026-01-07","firstquarter":"2017-12-31","lastquarter":"2025-09-30","secfilings":"https:\/\/www.sec.gov\/cgi-bin\/browse-edgar?action=getcompany&CIK=0001357874","companysite":"http:\/\/www.precisionbiosciences.com","open":4.27,"close":4.36,"high":4.61,"low":4.2,"volume":415265,"fxusd":1.0,"marketcap":51391281.0,"index":32299,"datekey":"2025-09-30","reportperiod":"2025-09-30T00:00:00.000","fiscalperiod":"2025-Q3","accoci":0.0,"assets":93510000.0,"assetsavg":115809250.0,"assetsc":51705000.0,"assetsnc":41805000.0,"assetturnover":0.006,"bvps":1.407,"capex":-141000.0,"cashneq":71212000.0,"cashnequsd":71212000.0,"cor":0.0,"consolinc":-83602000.0,"currentratio":3.448,"de":1.7511,"debt":29128000.0,"debtc":1458000.0,"debtnc":27670000.0,"debtusd":29128000.0,"deferredrev":36205000.0,"depamor":2832000.0,"deposits":0.0,"divyield":0.0,"dps":0.0,"ebit":-82136000.0,"ebitda":-79304000.0,"ebitdamargin":-113.616,"ebitdausd":-79304000.0,"ebitusd":-82136000.0,"ebt":-83602000.0,"eps":-9.0,"epsdil":-8.92,"epsusd":-9.0,"equity":16634000.0,"equityavg":39104500.0,"equityusd":16634000.0,"ev":9307281.0,"evebit":-0.11,"evebitda":-0.12,"fcf":-73417000.0,"fcfps":-6.212,"gp":698000.0,"grossmargin":1.0,"intangibles":985000.0,"intexp":1466000.0,"invcap":35445000.0,"invcapavg":39643000.0,"inventory":0.0,"investments":6114000.0,"investmentsc":0.0,"investmentsnc":6114000.0,"liabilities":76876000.0,"liabilitiesc":14996000.0,"liabilitiesnc":61880000.0,"ncf":-50116000.0,"ncfbus":0.0,"ncfcommon":23586000.0,"ncfdebt":-20000.0,"ncfdiv":0.0,"ncff":23566000.0,"ncfi":-406000.0,"ncfinv":0.0,"ncfo":-73276000.0,"ncfx":0.0,"netinc":-83602000.0,"netinccmn":-83602000.0,"netinccmnusd":-83602000.0,"netincdis":0.0,"netincnci":0.0,"netmargin":-119.774,"opex":90200000.0,"opinc":-89502000.0,"payables":1340000.0,"payoutratio":0.0,"pb":3.09,"pe":-0.778,"pe1":-0.48,"ppnenet":8164000.0,"prefdivis":0.0,"price":5.52,"ps":93.215,"ps1":73.63,"receivables":4000.0,"retearn":-548321000.0,"revenue":698000.0,"revenueusd":698000.0,"rnd":55615000.0,"roa":-0.722,"roe":-2.138,"roic":-2.072,"ros":-117.673,"sbcomp":11716000.0,"sgna":34585000.0,"sharefactor":1.0,"sharesbas":11786991.0,"shareswa":11818145.0,"shareswadil":11818145.0,"sps":0.059,"tangibles":92525000.0,"taxassets":0.0,"taxexp":0.0,"taxliabilities":0.0,"tbvps":7.829,"workingcapital":36709000.0,"date":"2025-09-30T00:00:00.000","shares":11786991.0,"net_workingcapital":-19982000.0,"discretionary_capex":-5434000.0,"fcfadj":-67842000.0,"fcfpsadj":-5.76,"revenuepct":-0.4465,"revenueyoy":-0.9907,"roc_revenueyoy":0.0052,"revenuecagr":-0.8847,"netincadj":-83602000.0,"epsadj":-7.09,"epspct":0.0436,"epsyoy":-101.0,"epsyoy1":-40.2083,"epsyoy_3q":0.0,"epsyoy_3q1":-0.1323,"epscagr":0.2342,"netinccagr":-0.0711,"ebitmargin":-117.6734,"ebitcagr":-0.0784,"ebitdacagr":-0.1461,"ebitdayoy":-5.9664,"peg":0.01,"dpscagr":0.0,"dpscagr5y":0.0,"dpscagr10y":0.0,"epsrank":0,"fcfpct":-0.0703,"fcfyoy":0.0611,"fcfcagr":0.3273,"fcfadjyoy":0.2549,"fcfadjcagr":0.3615,"fcfusd":-73417000.0,"avgroa":-0.2861,"avgroe":-1.0484,"avgroic":-3.2195,"roce":-1.0461,"avgroce":-0.4225,"fcfadjusd":-67842000.0,"cfc":0.8187,"icr":-56.03,"netdebt":-42084000.0,"dtfcf":-0.5732,"dtebitda":0.5307,"quickratio":5.1567,"reinvestrate":-0.276,"debtyield":0.0004,"bbyield":-0.4589,"shyield":-0.4589,"FS_ROA":0,"FCFTA":-0.7851245856,"FS_FCFTA":0,"ACCRUAL":-0.1891990161,"FS_ACCRUAL":0,"FS_\u0394LEVER":0,"FS_\u0394LIQUID":0,"FS_NEQISS":0,"FS_\u0394ROA":0,"FS_\u0394FCFTA":0,"FS_\u0394MARGIN":0,"FS_\u0394TURN":0,"fsscore":0,"smrrank":0,"evrevenue":13.33,"ipb":3.28,"fcfyield":-1.4286,"returnytd":4.81,"volumeavg3m":214927,"beta1y":0.58,"volumeusd":1809400.0,"pct":3.56,"close1":4.21,"volume1":183000.0,"low1":4.11,"high1":4.245,"pct1":3.19,"maxc20":5.01,"minc20":4.08,"max252":8.82,"min252":3.89,"maxc252":8.61,"minc252":4.08,"chg5":-1.36,"chg10":0.46,"chg1m":-13.15,"chg1q":-23.24,"chg2q":-7.82,"chg3q":-0.91,"chg1y":-8.21,"rs1y":-12.684,"adx":48.5623820548,"max_adx20":50.5736453294,"roc20":-0.084,"roc100":-0.086,"roc200":-0.2,"mom3":0.8838028169,"mom6":1.0613107822,"mom12":1.0568421053,"sma5":4.182,"sma10":4.247,"sma20":4.499,"sma50":5.38,"sma100":5.3764,"sma150":5.1550666667,"sma200":5.108175,"sma250":5.11546,"ema5":4.2466673032,"ema8":4.2686222941,"ema10":4.2971438739,"ema12":4.3311114202,"ema15":4.3883073626,"ema20":4.4924506176,"ema26":4.6181630853,"tenkan_sen":4.25,"kijun_sen":4.7125,"senkou_span_a":6.011,"senkou_span_b":6.675,"senkou_span_b1":6.66,"chikou_span":null,"avgvolume":224678.0,"avgvolumeusd":1184317.72,"avgvolumeusd1m":1122921.3,"adr":0.2736,"atr":0.2893677501,"std20":43.42,"std60":75.82,"std100":67.71,"std252":74.66,"rv3":35.02,"rv5":61.9,"rv20":43.81,"rv60":75.87,"rv100":67.65,"rv252":73.21,"ADline":-505477.2884180342,"ADscore":86.2587371091,"ADrank":53,"rsrank":25,"rank_mom6":62,"rank_mom12":59,"rank_mom3":29,"rank_volume3m":36,"rank_volume1m":38,"close_date":"2026-01-07T00:00:00.000","comprating":11,"qualrank":15,"finalcomp":10}]