[{"index":31799903,"ticker":"GLIBR","date":"2025-12-16T00:00:00.000","open":5.26,"high":9.92,"low":5.26,"volume":293000.0,"close":6.58,"volumeusd":1927940.0,"pct":6.13,"close1":6.2,"volume1":339000.0,"low1":4.81,"high1":6.3,"pct1":6.16,"maxc20":null,"minc20":null,"maxc252":null,"minc252":null,"chg5":42.42,"chg10":56.29,"chg1m":null,"chg1q":null,"chg2q":null,"chg3q":null,"chg1y":null,"rs1y":null,"adx":68.1613836792,"max_adx20":null,"roc20":null,"roc100":null,"roc200":null,"mom3":null,"mom6":null,"mom12":null,"sma5":5.8,"sma10":4.827,"sma18":null,"sma20":null,"sma50":null,"sma100":null,"sma150":null,"sma200":null,"sma250":null,"ema5":5.8572510213,"ema8":5.5652315651,"ema10":5.4789735821,"ema12":5.4431498054,"ema15":5.4415495941,"ema20":5.4975627887,"ema21":5.5121543375,"ema26":5.5882032015,"tenkan_sen":6.485,"kijun_sen":null,"senkou_span_a":null,"senkou_span_b":28.1669738248,"senkou_span_b1":28.1669738248,"chikou_span":null,"avgvolume":null,"avgvolumeusd":null,"avgvolumeusd1m":null,"adr":null,"atr":1.610771679,"std20":null,"std60":null,"std100":null,"std252":null,"rv3":37.72,"rv5":45.18,"rv20":null,"rv60":null,"rv100":null,"rv252":null,"ADline":null,"ADscore":50.0,"ADrank":0,"rsrank":0,"rank_mom6":0,"rank_mom12":0,"rank_mom3":0,"rank_volume3m":0,"rank_volume1m":0,"name":"GCI LIBERTY INC","sector":"Communication Services"}]