[{"ticker":"HBM","table":"SEP","permaticker":124672,"name":"HUDBAY MINERALS INC","exchange":"NYSE","isdelisted":false,"category":"Canadian Common Stock","cusips":"443628102","siccode":1000.0,"sicsector":"Mining","sicindustry":"Metal Mining","famasector":null,"famaindustry":"Non-Metallic and Industrial Metal Mining","sector":"Basic Materials","industry":"Copper","scalemarketcap":"4 - Mid","scalerevenue":"4 - Mid","relatedtickers":"HBMFF","currency":"USD","location":"Ontario; Canada","lastupdated":"2026-01-05","firstadded":"2016-11-15","firstpricedate":"2009-02-17","lastpricedate":"2026-01-05","firstquarter":"2004-12-31","lastquarter":"2025-09-30","secfilings":"https:\/\/www.sec.gov\/cgi-bin\/browse-edgar?action=getcompany&CIK=0001322422","companysite":"http:\/\/www.hudbayminerals.com","open":20.65,"close":21.3,"high":21.44,"low":20.54,"volume":3994300,"fxusd":1.0,"marketcap":8427738581.0,"index":444528,"datekey":"2025-09-30","reportperiod":"2025-09-30T00:00:00.000","fiscalperiod":"2025-Q3","accoci":0.0,"assets":5916800000.0,"assetsavg":5635000000.0,"assetsc":994300000.0,"assetsnc":4922500000.0,"assetturnover":0.366,"bvps":7.784,"capex":-420308000.0,"cashneq":611100000.0,"cashnequsd":611100000.0,"cor":1405485000.0,"consolinc":448563000.0,"currentratio":0.966,"de":0.4345,"debt":1338500000.0,"debtc":615600000.0,"debtnc":722900000.0,"debtusd":1338500000.0,"deferredrev":335900000.0,"depamor":410629000.0,"deposits":0.0,"divyield":null,"dps":0.007,"ebit":838723000.0,"ebitda":1249352000.0,"ebitdamargin":0.606,"ebitdausd":1249352000.0,"ebitusd":838723000.0,"ebt":771708000.0,"eps":1.16,"epsdil":1.16,"epsusd":1.16,"equity":3080500000.0,"equityavg":2787550000.0,"equityusd":3080500000.0,"ev":9155138581.0,"evebit":10.92,"evebitda":7.33,"fcf":319756000.0,"fcfps":0.808,"gp":657533000.0,"grossmargin":0.319,"intangibles":119800000.0,"intexp":67015000.0,"invcap":5495400000.0,"invcapavg":5514900000.0,"inventory":230800000.0,"investments":55600000.0,"investmentsc":300000.0,"investmentsnc":55300000.0,"liabilities":2836300000.0,"liabilitiesc":1029000000.0,"liabilitiesnc":1807300000.0,"ncf":167821000.0,"ncfbus":-2257000.0,"ncfcommon":27330000.0,"ncfdebt":-123331000.0,"ncfdiv":-5612000.0,"ncff":-187285000.0,"ncfi":-383738000.0,"ncfinv":17746000.0,"ncfo":740064000.0,"ncfx":-1220000.0,"netinc":468688000.0,"netinccmn":468688000.0,"netinccmnusd":468688000.0,"netincdis":0.0,"netincnci":6075000.0,"netmargin":0.227,"opex":-154595000.0,"opinc":812128000.0,"payables":263300000.0,"payoutratio":0.006,"pb":2.74,"pe":12.798,"pe1":18.36,"ppnenet":4634500000.0,"prefdivis":0.0,"price":15.16,"ps":2.908,"ps1":4.09,"receivables":160700000.0,"retearn":332500000.0,"revenue":2063018000.0,"revenueusd":2063018000.0,"rnd":45615000.0,"roa":0.083,"roe":0.168,"roic":0.152,"ros":0.407,"sbcomp":36258000.0,"sgna":75736000.0,"sharefactor":1.0,"sharesbas":395668478.0,"shareswa":395726407.0,"shareswadil":396886622.0,"sps":5.213,"tangibles":5797000000.0,"taxassets":94800000.0,"taxexp":303020000.0,"taxliabilities":434800000.0,"tbvps":14.649,"workingcapital":-34700000.0,"date":"2025-09-30T00:00:00.000","shares":395668478.0,"net_workingcapital":-61500000.0,"discretionary_capex":385387000.0,"fcfadj":354677000.0,"fcfpsadj":0.9,"revenuepct":-0.0631,"revenueyoy":0.012,"revenuecagr":0.21,"netincadj":468688000.0,"epsadj":1.18,"epspct":0.589,"epsyoy":3.64,"epsyoy1":1.92,"epsyoy_3q":-0.3603,"epsyoy_3q1":-0.402,"epscagr":5.2183,"netinccagr":4.0233,"ebitmargin":0.4066,"ebitcagr":1.5461,"ebitdacagr":0.6134,"ebitdayoy":0.6776,"peg":0.07,"dpscagr":-0.3168,"dpscagr5y":-0.1894,"dpscagr10y":-0.0734,"epsrank":82,"fcfpct":-0.1293,"fcfyoy":-0.0242,"fcfcagr":1.4741,"fcfadjyoy":0.8,"fcfadjcagr":0.8578,"fcfusd":319756000.0,"avgroa":0.0212,"avgroe":0.0471,"avgroic":0.0562,"roce":0.1716,"avgroce":0.0659,"fcfadjusd":354677000.0,"cfc":0.9113,"icr":12.52,"netdebt":727400000.0,"dtfcf":2.2749,"dtebitda":0.5822,"quickratio":0.8041,"reinvestrate":0.1017,"debtyield":0.0146,"bbyield":-0.0032,"shyield":-0.0029,"FS_ROA":1,"FCFTA":0.0540420498,"FS_FCFTA":1,"ACCRUAL":-0.0503601609,"FS_ACCRUAL":0,"FS_\u0394LEVER":1,"FS_\u0394LIQUID":0,"FS_NEQISS":0,"FS_\u0394ROA":1,"FS_\u0394FCFTA":0,"FS_\u0394MARGIN":0,"FS_\u0394TURN":0,"fsscore":4,"smrrank":78,"evrevenue":4.44,"ipb":2.85,"fcfyield":0.0379,"returnytd":7.3,"volumeavg3m":5492219,"beta1y":1.5,"volumeusd":85072200.0,"pct":5.97,"close1":20.1,"volume1":3582000.0,"low1":19.69,"high1":20.69,"pct1":1.26,"maxc20":21.3,"minc20":17.36,"max252":21.44,"min252":5.95,"maxc252":21.3,"minc252":6.09,"chg5":5.34,"chg10":12.28,"chg1m":22.48,"chg1q":35.32,"chg2q":95.23,"chg3q":199.58,"chg1y":163.22,"rs1y":105.734,"adx":12.4883819193,"max_adx20":19.1838564651,"roc20":0.2284,"roc100":1.1624,"roc200":1.5509,"mom3":1.1048284625,"mom6":1.5939505041,"mom12":2.149036085,"sma5":20.112,"sma10":19.957,"sma20":19.1455,"sma50":17.2532,"sma100":15.5673,"sma150":13.6816333333,"sma200":12.189425,"sma250":11.378696,"ema5":20.3573775304,"ema8":20.0859843869,"ema10":19.923728977,"ema12":19.7653294491,"ema15":19.5348772643,"ema20":19.178588468,"ema26":18.8021610099,"tenkan_sen":20.27,"kijun_sen":18.775,"senkou_span_a":15.775,"senkou_span_b":15.3645,"senkou_span_b1":15.3645,"chikou_span":null,"avgvolume":4979340.0,"avgvolumeusd":84972756.200000003,"avgvolumeusd1m":81458304.0,"adr":0.61425,"atr":0.7575190268,"std20":32.59,"std60":49.43,"std100":51.85,"std252":53.29,"rv3":50.01,"rv5":57.66,"rv20":32.29,"rv60":49.58,"rv100":51.06,"rv252":53.15,"ADline":-2678286.4528946783,"ADscore":86.5812819801,"ADrank":37,"rsrank":95,"rank_mom6":90,"rank_mom12":94,"rank_mom3":81,"rank_volume3m":83,"rank_volume1m":84,"close_date":"2026-01-05T00:00:00.000","comprating":94,"qualrank":75,"finalcomp":94}]