[{"ticker":"JRVR","table":"SEP","permaticker":187805,"name":"JAMES RIVER GROUP HOLDINGS INC","exchange":"NASDAQ","isdelisted":false,"category":"Domestic Common Stock","cusips":"G5005R107 46990A102","siccode":6331.0,"sicsector":"Finance Insurance And Real Estate","sicindustry":"Fire Marine & Casualty Insurance","famasector":null,"famaindustry":"Insurance","sector":"Financial Services","industry":"Insurance - Specialty","scalemarketcap":"3 - Small","scalerevenue":"3 - Small","relatedtickers":null,"currency":"USD","location":"Bermuda","lastupdated":"2026-01-05","firstadded":"2016-03-22","firstpricedate":"2014-12-12","lastpricedate":"2026-01-05","firstquarter":"2012-12-31","lastquarter":"2025-09-30","secfilings":"https:\/\/www.sec.gov\/cgi-bin\/browse-edgar?action=getcompany&CIK=0001620459","companysite":"http:\/\/www.jrgh.net","open":6.14,"close":6.14,"high":6.24,"low":6.04,"volume":229169,"fxusd":1.0,"marketcap":281927021.0,"index":509239,"datekey":"2025-09-30","reportperiod":"2025-09-30T00:00:00.000","fiscalperiod":"2025-Q3","accoci":-39005000.0,"assets":4950271000.0,"assetsavg":4981171000.0,"assetsc":null,"assetsnc":null,"assetturnover":0.13,"bvps":10.942,"capex":-5073000.0,"cashneq":268382000.0,"cashnequsd":268382000.0,"cor":478230000.0,"consolinc":-49413000.0,"currentratio":null,"de":0.518,"debt":329855000.0,"debtc":null,"debtnc":null,"debtusd":329855000.0,"deferredrev":489097000.0,"depamor":-709000.0,"deposits":0.0,"divyield":0.65,"dps":0.04,"ebit":-26730000.0,"ebitda":-27439000.0,"ebitdamargin":-0.042,"ebitdausd":-27439000.0,"ebitusd":-26730000.0,"ebt":-50009000.0,"eps":-2.21,"epsdil":-2.22,"epsusd":-2.21,"equity":636753000.0,"equityavg":485397750.0,"equityusd":503638000.0,"ev":343400021.0,"evebit":-12.85,"evebitda":-12.52,"fcf":10402000.0,"fcfps":0.226,"gp":168350000.0,"grossmargin":0.26,"intangibles":214009000.0,"intexp":23279000.0,"invcap":4797735000.0,"invcapavg":4786323000.0,"inventory":0.0,"investments":1746204000.0,"investmentsc":null,"investmentsnc":null,"liabilities":4313518000.0,"liabilitiesc":null,"liabilitiesnc":null,"ncf":-119755000.0,"ncfbus":0.0,"ncfcommon":0.0,"ncfdebt":23821000.0,"ncfdiv":-1965000.0,"ncff":25528000.0,"ncfi":-267612000.0,"ncfinv":-369690000.0,"ncfo":15475000.0,"ncfx":0.0,"netinc":-49413000.0,"netinccmn":-84594000.0,"netinccmnusd":-84594000.0,"netincdis":3719000.0,"netincnci":0.0,"netmargin":-0.131,"opex":191361000.0,"opinc":-23011000.0,"payables":92979000.0,"payoutratio":-0.018,"pb":0.56,"pe":-3.012,"pe1":-2.78,"ppnenet":0.0,"prefdivis":35181000.0,"price":5.55,"ps":0.394,"ps1":0.44,"receivables":521006000.0,"retearn":-394372000.0,"revenue":646580000.0,"revenueusd":646580000.0,"rnd":0.0,"roa":-0.017,"roe":-0.174,"roic":-0.006,"ros":-0.041,"sbcomp":7371000.0,"sgna":0.0,"sharefactor":1.0,"sharesbas":45916453.0,"shareswa":46026399.0,"shareswadil":46026399.0,"sps":14.048,"tangibles":4736262000.0,"taxassets":0.0,"taxexp":-596000.0,"taxliabilities":0.0,"tbvps":102.903,"workingcapital":null,"date":"2025-09-30T00:00:00.000","shares":45916453.0,"net_workingcapital":0.0,"discretionary_capex":6662000.0,"fcfadj":5094000.0,"fcfpsadj":0.11,"revenuepct":-0.0282,"revenueyoy":-0.1908,"revenuecagr":-0.0179,"netincadj":-53132000.0,"epsadj":-1.16,"epspct":0.3283,"epsyoy":0.5288,"epsyoy1":-0.0478,"epsyoy_3q":0.2576,"epsyoy_3q1":0.2557,"epscagr":0.0,"netinccagr":0.0,"ebitmargin":-0.0413,"ebitcagr":0.0,"ebitdacagr":0.0,"ebitdayoy":0.789,"peg":null,"dpscagr":-0.5528,"dpscagr5y":-0.4936,"dpscagr10y":-0.2201,"epsrank":49,"fcfpct":1.0354,"fcfyoy":1.0318,"fcfcagr":-0.7581,"fcfadjyoy":1.009,"fcfadjcagr":-0.828,"fcfusd":10402000.0,"avgroa":-0.0141,"avgroe":-0.1368,"avgroic":-0.0038,"roce":-0.0054,"avgroce":-0.0036,"fcfadjusd":5094000.0,"cfc":-0.6725,"icr":-1.15,"netdebt":61473000.0,"dtfcf":5.9097,"dtebitda":-2.2404,"quickratio":null,"reinvestrate":0.0,"debtyield":-0.0845,"bbyield":0.0,"shyield":0.0065,"FS_ROA":0,"FCFTA":0.0021012991,"FS_FCFTA":1,"ACCRUAL":-0.0123566972,"FS_ACCRUAL":1,"FS_\u0394LEVER":1,"FS_\u0394LIQUID":0,"FS_NEQISS":0,"FS_\u0394ROA":1,"FS_\u0394FCFTA":1,"FS_\u0394MARGIN":1,"FS_\u0394TURN":0,"fsscore":6,"smrrank":13,"evrevenue":0.53,"ipb":0.97,"fcfyield":0.0369,"returnytd":-3.46,"volumeavg3m":227672,"beta1y":0.56,"volumeusd":1406060.0,"pct":-0.32,"close1":6.16,"volume1":206000.0,"low1":6.074,"high1":6.38,"pct1":-3.14,"maxc20":6.79,"minc20":5.941,"max252":6.89,"min252":2.9769230769,"maxc252":6.79,"minc252":3.483,"chg5":-3.91,"chg10":-6.12,"chg1m":4.94,"chg1q":10.0,"chg2q":10.81,"chg3q":52.74,"chg1y":27.04,"rs1y":22.118,"adx":20.8884070585,"max_adx20":24.6964403092,"roc20":0.0318,"roc100":0.0714,"roc200":0.5784,"mom3":1.0481906127,"mom6":1.05594658,"mom12":1.2106352162,"sma5":6.274,"sma10":6.307,"sma20":6.3832,"sma50":5.88216,"sma100":5.68919,"sma150":5.6935533333,"sma200":5.420175,"sma250":5.247188,"ema5":6.2471665301,"ema8":6.2884990999,"ema10":6.3019738902,"ema12":6.3060149253,"ema15":6.2987446925,"ema20":6.2652449618,"ema26":6.2106600927,"tenkan_sen":6.26,"kijun_sen":6.2855853448,"senkou_span_a":5.5753960649,"senkou_span_b":5.491806674,"senkou_span_b1":5.491806674,"chikou_span":null,"avgvolume":241670.0,"avgvolumeusd":1443286.54,"avgvolumeusd1m":1837401.0,"adr":0.2177455929,"atr":0.2155076537,"std20":36.41,"std60":48.51,"std100":44.39,"std252":51.52,"rv3":25.04,"rv5":26.46,"rv20":36.36,"rv60":47.33,"rv100":43.58,"rv252":53.87,"ADline":1082953.9944669902,"ADscore":86.7109011969,"ADrank":84,"rsrank":74,"rank_mom6":59,"rank_mom12":72,"rank_mom3":72,"rank_volume3m":39,"rank_volume1m":43,"close_date":"2026-01-05T00:00:00.000","comprating":67,"qualrank":4,"finalcomp":39}]