[{"index":5051872,"ticker":"MLPI","date":"2026-01-09T00:00:00.000","open":50.18,"high":50.18,"low":49.35,"volume":185000.0,"close":49.51,"volumeusd":9159350.0,"pct":-0.26,"close1":49.64,"volume1":170000.0,"low1":49.41,"high1":49.88,"pct1":0.67,"maxc20":null,"minc20":null,"max252":null,"min252":null,"maxc252":null,"minc252":null,"minc1000":null,"maxc1000":null,"chg5":-2.02,"chg10":-1.18,"chg1m":null,"chg1q":null,"chg2q":null,"chg3q":null,"chg1y":null,"rs1y":null,"adx":78.9622993074,"max_adx20":null,"roc20":null,"roc100":null,"roc200":null,"mom3":null,"mom6":null,"mom12":null,"sma5":49.63,"sma10":49.93,"sma20":null,"sma50":null,"sma100":null,"sma150":null,"sma200":null,"sma250":null,"ema5":49.6532378299,"ema8":49.7629839564,"ema10":49.8096375167,"ema12":49.8413316606,"ema15":49.8708229225,"ema20":49.8939267055,"ema26":49.9026636663,"ema50":49.8943124831,"ema100":49.8716996832,"ema200":49.8536256024,"tenkan_sen":50.295,"kijun_sen":null,"senkou_span_a":null,"senkou_span_b":10.123,"senkou_span_b1":10.136,"chikou_span":null,"avgvolume":null,"avgvolumeusd":null,"avgvolumeusd1m":null,"adr":null,"atr":0.8180907957,"std20":null,"std60":null,"std100":null,"std252":null,"rv20":null,"rv60":null,"rv100":null,"rv252":null,"ADline":null,"ADscore":50.0,"ADrank":0,"rsrank":0,"rank_mom6":0,"rank_mom12":0,"rank_mom3":0,"rank_volume3m":0,"rank_volume1m":0,"name":"NEOS MLP & ENERGY INFRASTRUCTURE HIGH INCOME ETF"}]