[{"ticker":"UPWK","table":"SEP","permaticker":114650,"name":"UPWORK INC","exchange":"NASDAQ","isdelisted":false,"category":"Domestic Common Stock","cusips":"91688F104","siccode":7374.0,"sicsector":"Services","sicindustry":"Services-Computer Processing & Data Preparation","famasector":null,"famaindustry":"Business Services","sector":"Industrials","industry":"Staffing & Employment Services","scalemarketcap":"4 - Mid","scalerevenue":"3 - Small","relatedtickers":null,"currency":"USD","location":"California; U.S.A","lastupdated":"2026-01-02","firstadded":"2018-10-03","firstpricedate":"2018-10-03","lastpricedate":"2026-01-02","firstquarter":"2016-12-31","lastquarter":"2025-09-30","secfilings":"https:\/\/www.sec.gov\/cgi-bin\/browse-edgar?action=getcompany&CIK=0001627475","companysite":"http:\/\/www.upwork.com","open":19.8,"close":19.84,"high":20.17,"low":19.723,"volume":1507898,"fxusd":1.0,"marketcap":2630914527.0,"index":238623,"datekey":"2025-09-30","reportperiod":"2025-09-30T00:00:00.000","fiscalperiod":"2025-Q3","accoci":867000.0,"assets":1311209000.0,"assetsavg":1256151000.0,"assetsc":948951000.0,"assetsnc":362258000.0,"assetturnover":0.622,"bvps":4.759,"capex":-22576000.0,"cashneq":260838000.0,"cashnequsd":260838000.0,"cor":173722000.0,"consolinc":246957000.0,"currentratio":1.437,"de":0.5882,"debt":369441000.0,"debtc":359310000.0,"debtnc":10131000.0,"debtusd":369441000.0,"deferredrev":7943000.0,"depamor":24029000.0,"deposits":0.0,"divyield":0.0,"dps":0.0,"ebit":137496000.0,"ebitda":161525000.0,"ebitdamargin":0.207,"ebitdausd":161525000.0,"ebitusd":137496000.0,"ebt":137496000.0,"eps":1.85,"epsdil":1.74,"epsusd":1.85,"equity":628126000.0,"equityavg":601624750.0,"equityusd":628126000.0,"ev":2739517527.0,"evebit":19.92,"evebitda":16.96,"fcf":170471000.0,"fcfps":1.292,"gp":607136000.0,"grossmargin":0.778,"intangibles":190127000.0,"intexp":0.0,"invcap":569209000.0,"invcapavg":811688750.0,"inventory":0.0,"investments":382259000.0,"investmentsc":382259000.0,"investmentsnc":0.0,"liabilities":683083000.0,"liabilitiesc":660476000.0,"liabilitiesnc":22607000.0,"ncf":-30855000.0,"ncfbus":-74179000.0,"ncfcommon":-95759000.0,"ncfdebt":0.0,"ncfdiv":0.0,"ncff":-64693000.0,"ncfi":-159209000.0,"ncfinv":-62454000.0,"ncfo":193047000.0,"ncfx":0.0,"netinc":246957000.0,"netinccmn":246957000.0,"netinccmnusd":246957000.0,"netincdis":0.0,"netincnci":0.0,"netmargin":0.316,"opex":492540000.0,"opinc":114596000.0,"payables":8514000.0,"payoutratio":0.0,"pb":4.19,"pe":9.971,"pe1":10.72,"ppnenet":45561000.0,"prefdivis":0.0,"price":18.57,"ps":3.154,"ps1":3.37,"receivables":76433000.0,"retearn":21315000.0,"revenue":780858000.0,"revenueusd":780858000.0,"rnd":191980000.0,"roa":0.197,"roe":0.41,"roic":0.169,"ros":0.176,"sbcomp":61671000.0,"sgna":291907000.0,"sharefactor":1.0,"sharesbas":132606579.0,"shareswa":131987000.0,"shareswadil":139666000.0,"sps":5.916,"tangibles":1121082000.0,"taxassets":125065000.0,"taxexp":-109461000.0,"taxliabilities":0.0,"tbvps":8.494,"workingcapital":288475000.0,"date":"2025-09-30T00:00:00.000","shares":132606579.0,"net_workingcapital":-370884000.0,"discretionary_capex":-285184000.0,"fcfadj":478231000.0,"fcfpsadj":3.61,"revenuepct":0.0103,"revenueyoy":0.025,"revenuecagr":0.0823,"netincadj":246957000.0,"epsadj":1.86,"epspct":0.0054,"epsyoy":1.8462,"epsyoy1":2.2857,"epsyoy_3q":-0.2838,"epsyoy_3q1":0.0313,"epscagr":3.5338,"netinccagr":3.3563,"ebitmargin":0.1761,"ebitcagr":2.1752,"ebitdacagr":1.5652,"ebitdayoy":0.5327,"peg":0.09,"dpscagr":0.0,"dpscagr5y":0.0,"dpscagr10y":0.0,"epsrank":96,"fcfpct":0.0821,"fcfyoy":0.4167,"fcfcagr":1.2825,"fcfadjyoy":121.3333,"fcfadjcagr":1.9684,"fcfusd":170471000.0,"avgroa":0.077,"avgroe":0.163,"avgroic":0.0626,"roce":0.2113,"avgroce":0.0596,"fcfadjusd":478231000.0,"cfc":1.6846,"icr":null,"netdebt":108603000.0,"dtfcf":0.6371,"dtebitda":0.6724,"quickratio":1.0894,"reinvestrate":1.5077,"debtyield":0.0,"bbyield":0.0364,"shyield":0.0364,"FS_ROA":1,"FCFTA":0.1300105475,"FS_FCFTA":1,"ACCRUAL":0.0236499292,"FS_ACCRUAL":0,"FS_\u0394LEVER":1,"FS_\u0394LIQUID":0,"FS_NEQISS":0,"FS_\u0394ROA":0,"FS_\u0394FCFTA":1,"FS_\u0394MARGIN":0,"FS_\u0394TURN":0,"fsscore":4,"smrrank":83,"evrevenue":3.51,"ipb":6.01,"fcfyield":0.0648,"returnytd":0.1,"volumeavg3m":3511578,"beta1y":1.11,"volumeusd":29918720.0,"pct":0.1,"close1":19.82,"volume1":1612000.0,"low1":19.3,"high1":20.12,"pct1":1.38,"maxc20":21.95,"minc20":19.55,"max252":22.32,"min252":11.13,"maxc252":21.95,"minc252":11.75,"chg5":-5.39,"chg10":-1.73,"chg1m":-3.36,"chg1q":9.25,"chg2q":45.45,"chg3q":48.17,"chg1y":19.45,"rs1y":26.314,"adx":14.5373947412,"max_adx20":18.5529291306,"roc20":0.0056,"roc100":0.4795,"roc200":0.5019,"mom3":1.1305066079,"mom6":1.5051319648,"mom12":1.2360024082,"sma5":20.072,"sma10":20.451,"sma20":20.6195,"sma50":18.7346,"sma100":17.68805,"sma150":16.3113333333,"sma200":15.792775,"sma250":15.7375,"ema5":20.0456450463,"ema8":20.2223533176,"ema10":20.2891669038,"ema12":20.3196315993,"ema15":20.3120390052,"ema20":20.2094234283,"ema26":20.0186603694,"tenkan_sen":20.375,"kijun_sen":20.665,"senkou_span_a":17.1875,"senkou_span_b":18.075,"senkou_span_b1":18.075,"chikou_span":null,"avgvolume":3867400.0,"avgvolumeusd":72345347.400000006,"avgvolumeusd1m":52441958.0,"adr":0.7786,"atr":0.7896811779,"std20":48.36,"std60":61.23,"std100":55.0,"std252":53.49,"rv3":42.47,"rv5":33.11,"rv20":48.07,"rv60":60.26,"rv100":54.27,"rv252":52.57,"ADline":-13867111.7266906388,"ADscore":85.936198687,"ADrank":19,"rsrank":79,"rank_mom6":90,"rank_mom12":75,"rank_mom3":85,"rank_volume3m":82,"rank_volume1m":79,"close_date":"2026-01-02T00:00:00.000","comprating":93,"qualrank":96,"finalcomp":95}]